fast_sudoku_solver/__init__.py
fast_sudoku_solver/__main__.py
fast_sudoku_solver/services.py
fast_sudoku_solver/sudoku_solver.py
fast_sudoku_solver/techniques.py
fast_sudoku_solver-1.0.1.dist-info/LICENSE
fast_sudoku_solver-1.0.1.dist-info/METADATA
fast_sudoku_solver-1.0.1.dist-info/WHEEL
fast_sudoku_solver-1.0.1.dist-info/entry_points.txt
fast_sudoku_solver-1.0.1.dist-info/RECORD
