Metadata-Version: 2.1
Name: fast_sudoku_solver
Version: 1.0.1
Summary: A fast Python Sudoku Solver for 9x9 puzzles using constraint propagation and brute force, powered by NumPy and with a command-line interface.
Home-page: https://github.com/CassiusCle/fast_sudoku_solver
License: MIT
Keywords: sudoku,solver,fast,constraint,propagation,brute,force
Author: CassiusCle
Requires-Python: >=3.11
Classifier: License :: OSI Approved :: MIT License
Classifier: Programming Language :: Python :: 3
Classifier: Programming Language :: Python :: 3.11
Classifier: Programming Language :: Python :: 3.12
Requires-Dist: numpy (>=1.23.2)
Project-URL: Repository, https://github.com/CassiusCle/fast_sudoku_solver
